psgen/__init__.py
psgen/__main__.py
psgen/funcs.py
psgen/psgen.py
psgen-1.0.4.dist-info/LICENSE
psgen-1.0.4.dist-info/METADATA
psgen-1.0.4.dist-info/WHEEL
psgen-1.0.4.dist-info/entry_points.txt
psgen-1.0.4.dist-info/top_level.txt
psgen-1.0.4.dist-info/RECORD
