Metadata-Version: 2.1
Name: psgen
Version: 1.0.4
Summary: Random Password Generator
Home-page: https://nneji123.github.io/psgen/
Author: Ifeanyi Nneji
Author-email: ifeanyinneji@gmail.com
License: MIT
Project-URL: Funding, https://github.com/sponsors/Nneji123
Project-URL: Source, https://github.com/Nneji123/psgen
Classifier: Development Status :: 5 - Production/Stable
Classifier: Environment :: Console
Classifier: Intended Audience :: Developers
Classifier: License :: OSI Approved :: MIT License
Classifier: Operating System :: OS Independent
Classifier: Natural Language :: English
Classifier: Topic :: Internet :: WWW/HTTP
Classifier: Topic :: Software Development :: Code Generators
Classifier: Programming Language :: Python :: 3
Classifier: Programming Language :: Python :: 3.7
Classifier: Programming Language :: Python :: 3.8
Classifier: Programming Language :: Python :: 3.9
Classifier: Programming Language :: Python :: 3.10
Requires-Python: >=3.7
License-File: LICENSE
